<?xml version="1.0" encoding="utf-8"?>
<ArrayOfstring xmlns:i="http://www.w3.org/2001/XMLSchema-instance" xmlns="http://schemas.microsoft.com/2003/10/Serialization/Arrays">
	<string> -p </string>
	<string> --no-stat </string>
	<string> -U&lt;n&gt; </string>
	<string> --unified=&lt;n&gt; </string>
	<string> --output=&lt;file&gt; </string>
	<string> --output-indicator-new=&lt;char&gt; </string>
	<string> --output-indicator-old=&lt;char&gt; </string>
	<string> --output-indicator-context=&lt;char&gt; </string>
	<string> --indent-heuristic </string>
	<string> --no-indent-heuristic </string>
	<string> --minimal </string>
	<string> --patience </string>
	<string> --histogram </string>
	<string> --anchored=&lt;text&gt; </string>
	<string> --diff-algorithm={patience|minimal|histogram|myers} </string>
	<string> default, myers </string>
	<string> minimal </string>
	<string> patience </string>
	<string> histogram </string>
	<string> --stat[=&lt;width&gt;[,&lt;name-width&gt;[,&lt;count&gt;]]] </string>
	<string> --compact-summary </string>
	<string> --numstat </string>
	<string> --shortstat </string>
	<string> -X[&lt;param1,param2,…​&gt;] </string>
	<string> --dirstat[=&lt;param1,param2,…​&gt;] </string>
	<string> changes </string>
	<string> lines </string>
	<string> files </string>
	<string> cumulative </string>
	<string> &lt;limit&gt; </string>
	<string> --cumulative </string>
	<string> --dirstat-by-file[=&lt;param1,param2&gt;…​] </string>
	<string> --summary </string>
	<string> --no-renames </string>
	<string> --[no-]rename-empty </string>
	<string> --full-index </string>
	<string> --binary </string>
	<string> --abbrev[=&lt;n&gt;] </string>
	<string> -B[&lt;n&gt;][/&lt;m&gt;] </string>
	<string> --break-rewrites[=[&lt;n&gt;][/&lt;m&gt;]] </string>
	<string> -M[&lt;n&gt;] </string>
	<string> --find-renames[=&lt;n&gt;] </string>
	<string> -C[&lt;n&gt;] </string>
	<string> --find-copies[=&lt;n&gt;] </string>
	<string> --find-copies-harder </string>
	<string> -D </string>
	<string> --irreversible-delete </string>
	<string> -l&lt;num&gt; </string>
	<string> -O&lt;orderfile&gt; </string>
	<string> -a </string>
	<string> --text </string>
	<string> --ignore-cr-at-eol </string>
	<string> --ignore-space-at-eol </string>
	<string> -b </string>
	<string> --ignore-space-change </string>
	<string> -w </string>
	<string> --ignore-all-space </string>
	<string> --ignore-blank-lines </string>
	<string> --inter-hunk-context=&lt;lines&gt; </string>
	<string> -W </string>
	<string> --function-context </string>
	<string> --ext-diff </string>
	<string> --no-ext-diff </string>
	<string> --textconv </string>
	<string> --no-textconv </string>
	<string> --ignore-submodules[=&lt;when&gt;] </string>
	<string> --src-prefix=&lt;prefix&gt; </string>
	<string> --dst-prefix=&lt;prefix&gt; </string>
	<string> --no-prefix </string>
	<string> --line-prefix=&lt;prefix&gt; </string>
	<string> --ita-invisible-in-index </string>
	<string> -&lt;n&gt; </string>
	<string> -o &lt;dir&gt; </string>
	<string> --output-directory &lt;dir&gt; </string>
	<string> -n </string>
	<string> --numbered </string>
	<string> -N </string>
	<string> --no-numbered </string>
	<string> --start-number &lt;n&gt; </string>
	<string> --numbered-files </string>
	<string> -k </string>
	<string> --keep-subject </string>
	<string> -s </string>
	<string> --signoff </string>
	<string> --stdout </string>
	<string> --attach[=&lt;boundary&gt;] </string>
	<string> --no-attach </string>
	<string> --inline[=&lt;boundary&gt;] </string>
	<string> --thread[=&lt;style&gt;] </string>
	<string> --no-thread </string>
	<string> --in-reply-to=&lt;message id&gt; </string>
	<string> --ignore-if-in-upstream </string>
	<string> --cover-from-description=&lt;mode&gt; </string>
	<string> --subject-prefix=&lt;subject prefix&gt; </string>
	<string> --rfc </string>
	<string> -v &lt;n&gt; </string>
	<string> --reroll-count=&lt;n&gt; </string>
	<string> --to=&lt;email&gt; </string>
	<string> --cc=&lt;email&gt; </string>
	<string> --from </string>
	<string> --from=&lt;ident&gt; </string>
	<string> --add-header=&lt;header&gt; </string>
	<string> --[no-]cover-letter </string>
	<string> --encode-email-headers </string>
	<string> --no-encode-email-headers </string>
	<string> --interdiff=&lt;previous&gt; </string>
	<string> --range-diff=&lt;previous&gt; </string>
	<string> --creation-factor=&lt;percent&gt; </string>
	<string> --notes[=&lt;ref&gt;] </string>
	<string> --no-notes </string>
	<string> --[no-]signature=&lt;signature&gt; </string>
	<string> --signature-file=&lt;file&gt; </string>
	<string> --suffix=.&lt;sfx&gt; </string>
	<string> -q </string>
	<string> --quiet </string>
	<string> --no-binary </string>
	<string> --zero-commit </string>
	<string> --[no-]base[=&lt;commit&gt;] </string>
	<string> --root </string>
	<string> --progress </string>
</ArrayOfstring>